datatoolcute/__init__.py
datatoolcute/file/__init__.py
datatoolcute/pandas/__init__.py
datatoolcute/pandas/dframe.py
datatoolcute/pandas/multiframe.py
datatoolcute/pandas/utils.py
datatoolcute-0.1.0.dist-info/METADATA
datatoolcute-0.1.0.dist-info/WHEEL
datatoolcute-0.1.0.dist-info/top_level.txt
datatoolcute-0.1.0.dist-info/RECORD
