Metadata-Version: 2.1
Name: datatoolcute
Version: 0.1.0
Summary: A short description of your library
Author: Yves Augusto
Author-email: yvesromero1998@gmail.com
Classifier: Programming Language :: Python :: 3.11
Classifier: Operating System :: OS Independent
Requires-Python: >=3.11
Requires-Dist: python-Levenshtein>=0.25.1
Requires-Dist: pandas>=2.2.2
